adaptiq/__init__.py
adaptiq/cli.py
adaptiq/agents/__init__.py
adaptiq/agents/crew_ai/__init__.py
adaptiq/agents/crew_ai/crew_config.py
adaptiq/agents/crew_ai/crew_log_parser.py
adaptiq/agents/crew_ai/crew_logger.py
adaptiq/agents/crew_ai/crew_prompt_parser.py
adaptiq/agents/crew_ai/instrumental.py
adaptiq/cloud/__init__.py
adaptiq/cloud/adaptiq_client.py
adaptiq/cloud/http_client.py
adaptiq/core/__init__.py
adaptiq/core/abstract/__init__.py
adaptiq/core/abstract/integrations/__init__.py
adaptiq/core/abstract/integrations/base_agent_logger.py
adaptiq/core/abstract/integrations/base_config.py
adaptiq/core/abstract/integrations/base_instrumental.py
adaptiq/core/abstract/integrations/base_log_parser.py
adaptiq/core/abstract/integrations/base_prompt_parser.py
adaptiq/core/abstract/pipelines/__init__.py
adaptiq/core/abstract/pipelines/base_post_run.py
adaptiq/core/abstract/pipelines/base_pre_run.py
adaptiq/core/abstract/q_table/__init__.py
adaptiq/core/abstract/q_table/base_q_table_manager.py
adaptiq/core/abstract/q_table/base_state_mapper.py
adaptiq/core/entities/__init__.py
adaptiq/core/entities/adaptiq_config.py
adaptiq/core/entities/adaptiq_logs.py
adaptiq/core/entities/adaptiq_meterics.py
adaptiq/core/entities/adaptiq_parsers.py
adaptiq/core/entities/adaptiq_rewards.py
adaptiq/core/entities/q_table.py
adaptiq/core/pipelines/__init__.py
adaptiq/core/pipelines/post_run/__init__.py
adaptiq/core/pipelines/post_run/post_run.py
adaptiq/core/pipelines/post_run/tools/__init__.py
adaptiq/core/pipelines/post_run/tools/post_run_reconciler.py
adaptiq/core/pipelines/post_run/tools/post_run_updater.py
adaptiq/core/pipelines/post_run/tools/prompt_engineer.py
adaptiq/core/pipelines/pre_run/__init__.py
adaptiq/core/pipelines/pre_run/pre_run.py
adaptiq/core/pipelines/pre_run/tools/__init__.py
adaptiq/core/pipelines/pre_run/tools/hypothetical_state_generator.py
adaptiq/core/pipelines/pre_run/tools/prompt_consulting.py
adaptiq/core/pipelines/pre_run/tools/prompt_estimator.py
adaptiq-0.12.8.dist-info/licenses/LICENSE
adaptiq-0.12.8.dist-info/METADATA
adaptiq-0.12.8.dist-info/WHEEL
adaptiq-0.12.8.dist-info/entry_points.txt
adaptiq-0.12.8.dist-info/top_level.txt
adaptiq-0.12.8.dist-info/RECORD
