Metadata-Version: 2.4
Name: adaptiq
Version: 0.12.8
Summary: An offline Q-learning framework for AI agent prompt optimization.
Author-email: Youssef ALWAZ / KOSMOS Technologies <alwaz.youssef@kosmostechnologies.fr>, Wassim AMRI / KOSMOS Technologies <w.amri@kosmostechnologies.fr>
License:                                  Apache License
Keywords: ai,agent,reinforcement learning,q-learning,prompt engineering,llm,crewai
Classifier: Development Status :: 3 - Alpha
Classifier: Intended Audience :: Developers
Classifier: Intended Audience :: Science/Research
Classifier: License :: OSI Approved :: MIT License
Classifier: Operating System :: OS Independent
Classifier: Programming Language :: Python :: 3
Classifier: Programming Language :: Python :: 3.8
Classifier: Programming Language :: Python :: 3.9
Classifier: Programming Language :: Python :: 3.10
Classifier: Programming Language :: Python :: 3.11
Classifier: Programming Language :: Python :: 3.12
Classifier: Topic :: Scientific/Engineering :: Artificial Intelligence
Classifier: Topic :: Software Development :: Libraries :: Python Modules
Classifier: Topic :: Utilities
Requires-Python: >=3.11
License-File: LICENSE
Requires-Dist: crewai
Requires-Dist: crewai_tools
Requires-Dist: numpy
Requires-Dist: pyyaml
Requires-Dist: python-dotenv
Requires-Dist: scikit-learn
Requires-Dist: langchain
Requires-Dist: langchain-openai
Requires-Dist: openai-agents>=0.1.0
Dynamic: license-file
